README.md
setup.py
Pairs_Package/__init__.py
Pairs_Package/broker_info.py
Pairs_Package/data.py
Pairs_Package/signals.py
Pairs_Package/trade.py
Pairs_Package.egg-info/PKG-INFO
Pairs_Package.egg-info/SOURCES.txt
Pairs_Package.egg-info/dependency_links.txt
Pairs_Package.egg-info/requires.txt
Pairs_Package.egg-info/top_level.txt